nonebot_plugin_yinying_chat/ChatSession.py
nonebot_plugin_yinying_chat/__init__.py
nonebot_plugin_yinying_chat/config.py
nonebot_plugin_yinying_chat-2.2.dist-info/METADATA
nonebot_plugin_yinying_chat-2.2.dist-info/WHEEL
nonebot_plugin_yinying_chat-2.2.dist-info/top_level.txt
nonebot_plugin_yinying_chat-2.2.dist-info/RECORD
